astropy_sphinx_theme/__init__.py
astropy_sphinx_theme/version.py
astropy_sphinx_theme/bootstrap-astropy/globaltoc.html
astropy_sphinx_theme/bootstrap-astropy/layout.html
astropy_sphinx_theme/bootstrap-astropy/localtoc.html
astropy_sphinx_theme/bootstrap-astropy/searchbox.html
astropy_sphinx_theme/bootstrap-astropy/theme.conf
astropy_sphinx_theme/bootstrap-astropy/static/astropy_linkout.svg
astropy_sphinx_theme/bootstrap-astropy/static/astropy_linkout_20.png
astropy_sphinx_theme/bootstrap-astropy/static/astropy_logo.ico
astropy_sphinx_theme/bootstrap-astropy/static/astropy_logo.svg
astropy_sphinx_theme/bootstrap-astropy/static/astropy_logo_32.png
astropy_sphinx_theme/bootstrap-astropy/static/bootstrap-astropy.css
astropy_sphinx_theme/bootstrap-astropy/static/copybutton.js
astropy_sphinx_theme/bootstrap-astropy/static/sidebar.js
astropy_sphinx_theme/tests/__init__.py
astropy_sphinx_theme/tests/test_basic.py
astropy_sphinx_theme-2.0.dist-info/LICENSE.rst
astropy_sphinx_theme-2.0.dist-info/METADATA
astropy_sphinx_theme-2.0.dist-info/WHEEL
astropy_sphinx_theme-2.0.dist-info/entry_points.txt
astropy_sphinx_theme-2.0.dist-info/top_level.txt
astropy_sphinx_theme-2.0.dist-info/RECORD
