Metadata-Version: 2.1
Name: astropy-sphinx-theme
Version: 2.0
Summary: The sphinx theme for Astropy and affiliated packages.
Home-page: https://github.com/astropy/astropy-sphinx-theme
Author: The Astropy Developers
Author-email: astropy.team@gmail.com
License: BSD
Classifier: Development Status :: 3 - Alpha
Classifier: Intended Audience :: Developers
Classifier: License :: OSI Approved :: BSD License
Classifier: Operating System :: OS Independent
Classifier: Programming Language :: Python
Classifier: Programming Language :: Python :: Implementation :: CPython
Requires-Python: >=3.7
License-File: LICENSE.rst
Requires-Dist: setuptools>=30.3.0
Provides-Extra: test
Requires-Dist: packaging; extra == "test"
Requires-Dist: pytest; extra == "test"
Requires-Dist: sphinx; extra == "test"
